4chan-thread-archiver
README.rst
archive-nabber
setup.py
thread-archiver
BASC_Archiver.egg-info/PKG-INFO
BASC_Archiver.egg-info/SOURCES.txt
BASC_Archiver.egg-info/dependency_links.txt
BASC_Archiver.egg-info/requires.txt
BASC_Archiver.egg-info/top_level.txt
basc_archiver/__init__.py
basc_archiver/utils.py
basc_archiver/sites/__init__.py
basc_archiver/sites/base.py
basc_archiver/sites/fourchan.py
basc_archiver/sites/fourtwentychan.py
basc_archiver/sites/fuuka.py