Metadata-Version: 1.1
Name: BASC-Archiver
Version: 0.9.5
Summary: Makes a complete archive of imageboard threads including images, HTML, and JSON.
Home-page: https://github.com/bibanon/BASC-Archiver
Author: Lawrence Wu <sagnessagiel@gmail.com>, Daniel Oaks <daniel@danieloaks.net>
Author-email: sagnessagiel@gmail.com
License: UNKNOWN
Keywords: 4chan downloader images json dump
Platform: UNKNOWN
Classifier: Development Status :: 4 - Beta
Classifier: Intended Audience :: Developers
Classifier: Natural Language :: English
Classifier: Programming Language :: Python :: 2
Classifier: Programming Language :: Python :: 3
